infery.pyi
tests.pyi
infery.cpython-38-x86_64-linux-gnu.so
tests.cpython-38-x86_64-linux-gnu.so
infery-3.9.0.dist-info/top_level.txt
infery-3.9.0.dist-info/RECORD
infery-3.9.0.dist-info/METADATA
infery-3.9.0.dist-info/WHEEL
infery-3.9.0.dist-info/LICENSE
