Metadata-Version: 2.1
Name: infery
Version: 3.9.0
Summary: Deci Run-Time Engine
Home-page: https://github.com/Deci-AI/infery-examples
Author: Deci AI
Author-email: rnd@deci.ai
License: Deci Infery License
Keywords: Deci,AI,Inference,Deep Learning
Requires-Python: >=3.7.5
License-File: LICENSE
Requires-Dist: pydantic (==1.9.1)
Requires-Dist: psutil (==5.9.1)
Requires-Dist: requests (==2.28.1)
Requires-Dist: pandas (==1.3.4)
Requires-Dist: cryptography (==37.0.3)
Requires-Dist: numpy (==1.19.5)
Requires-Dist: typing-extensions (==4.4.0)
Provides-Extra: all
Requires-Dist: onnx (==1.12.0) ; extra == 'all'
Requires-Dist: onnxruntime (==1.10.0) ; extra == 'all'
Requires-Dist: tensorflow (==2.7.3) ; extra == 'all'
Requires-Dist: torch (==1.12.1) ; extra == 'all'
Requires-Dist: openvino (==2022.1) ; extra == 'all'
Requires-Dist: coremltools (==6.1) ; extra == 'all'
Provides-Extra: coreml
Requires-Dist: coremltools (==6.1) ; extra == 'coreml'
Provides-Extra: onnx
Requires-Dist: onnx (==1.12.0) ; extra == 'onnx'
Requires-Dist: onnxruntime (==1.10.0) ; extra == 'onnx'
Provides-Extra: openvino
Requires-Dist: openvino (==2022.1) ; extra == 'openvino'
Provides-Extra: openvino_21
Requires-Dist: openvino (==2021.4) ; extra == 'openvino_21'
Provides-Extra: openvino_22
Requires-Dist: openvino (==2022.1) ; extra == 'openvino_22'
Provides-Extra: tensorflow
Requires-Dist: tensorflow (==2.7.3) ; extra == 'tensorflow'
Provides-Extra: torch
Requires-Dist: torch (==1.12.1) ; extra == 'torch'
